ezga/__init__.py
ezga/factory.py
ezga/DoE/DoE.py
ezga/DoE/__init__.py
ezga/DoE/constraint.py
ezga/classification/__init__.py
ezga/classification/clustering.py
ezga/cli/__init__.py
ezga/cli/__main__.py
ezga/cli/resume.py
ezga/cli/run.py
ezga/cli/runners.py
ezga/cli/wizard.py
ezga/convergence/__init__.py
ezga/convergence/convergence.py
ezga/core/config.py
ezga/core/context.py
ezga/core/engine.py
ezga/core/interfaces.py
ezga/core/population.py
ezga/evaluator/__init__.py
ezga/evaluator/evaluator.py
ezga/evaluator/features.py
ezga/evaluator/objective.py
ezga/examples/config.xyz
ezga/examples/config.yaml
ezga/generative/__init__.py
ezga/generative/base.py
ezga/generative/models/BayesianOptimization.py
ezga/generative/models/bo_generative.py
ezga/hise/__init__.py
ezga/hise/manager.py
ezga/hise/manager_pre.py
ezga/hise/manager_pre1.py
ezga/hise/metadata.py
ezga/io/__init__.py
ezga/io/config_loader.py
ezga/io/io_manager.py
ezga/io/resume.py
ezga/io/snapshot_recorder.py
ezga/metric/__init__.py
ezga/metric/information_ensemble_metrics.py
ezga/selection/__init__.py
ezga/selection/multiobjective_selector.py
ezga/selection/ranking.py
ezga/selection/selector.py
ezga/simple/__init__.py
ezga/simple/algorithm.py
ezga/simple/ge.py
ezga/simple/grammar.py
ezga/simple/minimize.py
ezga/simple/operators.py
ezga/simple/ops.py
ezga/simple/problem.py
ezga/simple/result.py
ezga/simple/symbolic_adapter.py
ezga/simple/symbolic_regression.py
ezga/simulator/F_vib.py
ezga/simulator/__init__.py
ezga/simulator/ase_calculator.py
ezga/simulator/mace_calculator.py
ezga/simulator/mace_utils.py
ezga/simulator/simulator.py
ezga/simulator/vib_spectrum.py
ezga/simulator/calculators/LJ.py
ezga/simulator/calculators/__init__.py
ezga/simulator/calculators/calculator_interface.py
ezga/simulator/calculators/constant_zero.py
ezga/simulator/calculators/dimer_calculator.py
ezga/simulator/calculators/reactivity_calculator.py
ezga/sync/__init__.py
ezga/sync/agenticsync.py
ezga/sync/agenticsync_1.py
ezga_lib-0.0.57.dist-info/METADATA
ezga_lib-0.0.57.dist-info/WHEEL
ezga_lib-0.0.57.dist-info/entry_points.txt
ezga_lib-0.0.57.dist-info/RECORD
