Metadata-Version: 2.4
Name: ezga-lib
Version: 0.0.57
Summary: A modular multi-objective genetic algorithm framework for atomistic structure exploration
Project-URL: Homepage, https://thgitlab.rz-berlin.mpg.de/lombardi/ezga
Project-URL: Issues, https://thgitlab.rz-berlin.mpg.de/lombardi/ezga/issues
Author-email: Juan Manuel Lombardi <lombardi@fhi-berlin.mpg.de>
License: GPL-3.0-only
Keywords: DFT,MLIP,genetic algorithm,materials,multi-objective
Classifier: Development Status :: 3 - Alpha
Classifier: Intended Audience :: Science/Research
Classifier: License :: OSI Approved :: GNU General Public License v3 (GPLv3)
Classifier: Operating System :: OS Independent
Classifier: Programming Language :: Python :: 3
Classifier: Topic :: Scientific/Engineering :: Chemistry
Classifier: Topic :: Scientific/Engineering :: Physics
Requires-Python: >=3.10
Requires-Dist: ase>=3.22.1
Requires-Dist: matplotlib>=3.4
Requires-Dist: numpy>=1.26
Requires-Dist: psutil>=5.9
Requires-Dist: pydantic>=2.10
Requires-Dist: rich>=13.0
Requires-Dist: ruamel-yaml>=0.18
Requires-Dist: sage-lib>=0.1.6.3
Requires-Dist: scikit-learn>=1.4
Requires-Dist: scipy>=1.12
Requires-Dist: spglib
Requires-Dist: typer>=0.12
Requires-Dist: typing-extensions>=4.6
Provides-Extra: tests
Requires-Dist: pytest-cov>=4; extra == 'tests'
Requires-Dist: pytest>=7; extra == 'tests'
